{
  "rom": "starcrus",
  "game_context": {
    "class": "starcrus_state",
    "machine": "starcrus",
    "input": "starcrus"
  },
  "inputs": [
    {
      "input": "GAME_TIME",
      "input_id": "P1_GAME_TIME",
      "label": "Game Time",
      "function": "game_time",
      "control_type": "misc",
      "joystick_way": "",
      "port_block": "runtime",
      "tag": "DSW",
      "mask": "0x3",
      "mask_int": 3,
      "defvalue": "0x3",
      "defvalue_int": 3,
      "default_raw": "",
      "ipt": "",
      "keycode": "",
      "keycode_dec": "",
      "keycode_inc": "",
      "comment": "",
      "player": 1,
      "min": null,
      "max": null,
      "sensitivity": null,
      "keydelta": null,
      "centerdelta": null,
      "full_turn_count": null,
      "impulse": null,
      "reverse": false,
      "invert": false,
      "reset": false,
      "toggle": false,
      "condition": "",
      "mame_label": "",
      "mame_type": "5",
      "mame_tag": ":DSW",
      "cfg_tag": ":DSW"
    },
    {
      "input": "COINAGE",
      "input_id": "COINAGE",
      "label": "Coinage",
      "function": "coinage",
      "control_type": "only_buttons",
      "joystick_way": "",
      "port_block": "runtime",
      "tag": "DSW",
      "mask": "0x4",
      "mask_int": 4,
      "defvalue": "0x4",
      "defvalue_int": 4,
      "default_raw": "",
      "ipt": "",
      "keycode": "",
      "keycode_dec": "",
      "keycode_inc": "",
      "comment": "",
      "player": 1,
      "min": null,
      "max": null,
      "sensitivity": null,
      "keydelta": null,
      "centerdelta": null,
      "full_turn_count": null,
      "impulse": null,
      "reverse": false,
      "invert": false,
      "reset": false,
      "toggle": false,
      "condition": "",
      "mame_label": "",
      "mame_type": "5",
      "mame_tag": ":DSW",
      "cfg_tag": ":DSW"
    },
    {
      "input": "MODE",
      "input_id": "P1_MODE",
      "label": "Mode",
      "function": "mode",
      "control_type": "misc",
      "joystick_way": "",
      "port_block": "runtime",
      "tag": "DSW",
      "mask": "0x20",
      "mask_int": 32,
      "defvalue": "0x20",
      "defvalue_int": 32,
      "default_raw": "",
      "ipt": "",
      "keycode": "",
      "keycode_dec": "",
      "keycode_inc": "",
      "comment": "",
      "player": 1,
      "min": null,
      "max": null,
      "sensitivity": null,
      "keydelta": null,
      "centerdelta": null,
      "full_turn_count": null,
      "impulse": null,
      "reverse": false,
      "invert": false,
      "reset": false,
      "toggle": false,
      "condition": "",
      "mame_label": "",
      "mame_type": "5",
      "mame_tag": ":DSW",
      "cfg_tag": ":DSW"
    },
    {
      "input": "POT_NOISE_LEVEL",
      "input_id": "P1_POT_NOISE_LEVEL",
      "label": "Pot: Noise Level",
      "function": "pot_noise_level",
      "control_type": "misc",
      "joystick_way": "",
      "port_block": "runtime",
      "tag": "POT_1",
      "mask": "0xff",
      "mask_int": 255,
      "defvalue": "0xff",
      "defvalue_int": 255,
      "default_raw": "",
      "ipt": "",
      "keycode": "",
      "keycode_dec": "",
      "keycode_inc": "",
      "comment": "",
      "player": 1,
      "min": null,
      "max": null,
      "sensitivity": null,
      "keydelta": null,
      "centerdelta": null,
      "full_turn_count": null,
      "impulse": null,
      "reverse": false,
      "invert": false,
      "reset": false,
      "toggle": false,
      "condition": "",
      "mame_label": "",
      "mame_type": "168",
      "mame_tag": ":POT_1",
      "cfg_tag": ":POT_1"
    },
    {
      "input": "POT_VOLUME",
      "input_id": "P1_POT_VOLUME",
      "label": "Pot: Volume",
      "function": "pot_volume",
      "control_type": "misc",
      "joystick_way": "",
      "port_block": "runtime",
      "tag": "POT_2",
      "mask": "0xff",
      "mask_int": 255,
      "defvalue": "0xff",
      "defvalue_int": 255,
      "default_raw": "",
      "ipt": "",
      "keycode": "",
      "keycode_dec": "",
      "keycode_inc": "",
      "comment": "",
      "player": 1,
      "min": null,
      "max": null,
      "sensitivity": null,
      "keydelta": null,
      "centerdelta": null,
      "full_turn_count": null,
      "impulse": null,
      "reverse": false,
      "invert": false,
      "reset": false,
      "toggle": false,
      "condition": "",
      "mame_label": "",
      "mame_type": "168",
      "mame_tag": ":POT_2",
      "cfg_tag": ":POT_2"
    },
    {
      "input": "COIN2",
      "input_id": "COIN2",
      "label": "Coin 2",
      "function": "coin_2",
      "control_type": "only_buttons",
      "joystick_way": "",
      "port_block": "starcrus",
      "tag": "DSW",
      "mask": "0x8",
      "mask_int": 8,
      "defvalue": "0x8",
      "defvalue_int": 8,
      "default_raw": "IP_ACTIVE_LOW",
      "ipt": "IPT_COIN2",
      "keycode": "",
      "keycode_dec": "",
      "keycode_inc": "",
      "comment": "",
      "player": 1,
      "min": null,
      "max": null,
      "sensitivity": null,
      "keydelta": null,
      "centerdelta": null,
      "full_turn_count": null,
      "impulse": null,
      "reverse": false,
      "invert": false,
      "reset": false,
      "toggle": false,
      "condition": "",
      "mame_label": "Coin 2",
      "mame_type": "18",
      "mame_tag": ":DSW",
      "cfg_tag": ":DSW"
    },
    {
      "input": "COIN1",
      "input_id": "COIN1",
      "label": "Coin 1",
      "function": "coin_1",
      "control_type": "only_buttons",
      "joystick_way": "",
      "port_block": "starcrus",
      "tag": "DSW",
      "mask": "0x10",
      "mask_int": 16,
      "defvalue": "0x10",
      "defvalue_int": 16,
      "default_raw": "IP_ACTIVE_LOW",
      "ipt": "IPT_COIN1",
      "keycode": "",
      "keycode_dec": "",
      "keycode_inc": "",
      "comment": "",
      "player": 1,
      "min": null,
      "max": null,
      "sensitivity": null,
      "keydelta": null,
      "centerdelta": null,
      "full_turn_count": null,
      "impulse": null,
      "reverse": false,
      "invert": false,
      "reset": false,
      "toggle": false,
      "condition": "",
      "mame_label": "Coin 1",
      "mame_type": "17",
      "mame_tag": ":DSW",
      "cfg_tag": ":DSW"
    },
    {
      "input": "JOYSTICK_LEFT",
      "input_id": "P1_JOYSTICK_LEFT",
      "label": "ccw",
      "function": "ccw",
      "control_type": "joy2wayhorizontal",
      "joystick_way": "2way",
      "port_block": "starcrus",
      "tag": "P1",
      "mask": "0x1",
      "mask_int": 1,
      "defvalue": "0x1",
      "defvalue_int": 1,
      "default_raw": "IP_ACTIVE_LOW",
      "ipt": "IPT_JOYSTICK_LEFT",
      "keycode": "",
      "keycode_dec": "",
      "keycode_inc": "",
      "comment": "ccw",
      "player": 1,
      "min": null,
      "max": null,
      "sensitivity": null,
      "keydelta": null,
      "centerdelta": null,
      "full_turn_count": null,
      "impulse": null,
      "reverse": false,
      "invert": false,
      "reset": false,
      "toggle": false,
      "condition": "",
      "mame_label": "P1 Left",
      "mame_type": "49",
      "mame_tag": ":P1",
      "cfg_tag": ":P1"
    },
    {
      "input": "BUTTON2",
      "input_id": "P1_BUTTON2",
      "label": "engine",
      "function": "engine",
      "control_type": "only_buttons",
      "joystick_way": "",
      "port_block": "starcrus",
      "tag": "P1",
      "mask": "0x2",
      "mask_int": 2,
      "defvalue": "0x2",
      "defvalue_int": 2,
      "default_raw": "IP_ACTIVE_LOW",
      "ipt": "IPT_BUTTON2",
      "keycode": "",
      "keycode_dec": "",
      "keycode_inc": "",
      "comment": "engine",
      "player": 1,
      "min": null,
      "max": null,
      "sensitivity": null,
      "keydelta": null,
      "centerdelta": null,
      "full_turn_count": null,
      "impulse": null,
      "reverse": false,
      "invert": false,
      "reset": false,
      "toggle": false,
      "condition": "",
      "mame_label": "P1 Button 2",
      "mame_type": "61",
      "mame_tag": ":P1",
      "cfg_tag": ":P1"
    },
    {
      "input": "JOYSTICK_RIGHT",
      "input_id": "P1_JOYSTICK_RIGHT",
      "label": "cw",
      "function": "cw",
      "control_type": "joy2wayhorizontal",
      "joystick_way": "2way",
      "port_block": "starcrus",
      "tag": "P1",
      "mask": "0x4",
      "mask_int": 4,
      "defvalue": "0x4",
      "defvalue_int": 4,
      "default_raw": "IP_ACTIVE_LOW",
      "ipt": "IPT_JOYSTICK_RIGHT",
      "keycode": "",
      "keycode_dec": "",
      "keycode_inc": "",
      "comment": "cw",
      "player": 1,
      "min": null,
      "max": null,
      "sensitivity": null,
      "keydelta": null,
      "centerdelta": null,
      "full_turn_count": null,
      "impulse": null,
      "reverse": false,
      "invert": false,
      "reset": false,
      "toggle": false,
      "condition": "",
      "mame_label": "P1 Right",
      "mame_type": "50",
      "mame_tag": ":P1",
      "cfg_tag": ":P1"
    },
    {
      "input": "BUTTON3",
      "input_id": "P1_BUTTON3",
      "label": "torpedo",
      "function": "torpedo",
      "control_type": "only_buttons",
      "joystick_way": "",
      "port_block": "starcrus",
      "tag": "P1",
      "mask": "0x10",
      "mask_int": 16,
      "defvalue": "0x10",
      "defvalue_int": 16,
      "default_raw": "IP_ACTIVE_LOW",
      "ipt": "IPT_BUTTON3",
      "keycode": "",
      "keycode_dec": "",
      "keycode_inc": "",
      "comment": "torpedo",
      "player": 1,
      "min": null,
      "max": null,
      "sensitivity": null,
      "keydelta": null,
      "centerdelta": null,
      "full_turn_count": null,
      "impulse": null,
      "reverse": false,
      "invert": false,
      "reset": false,
      "toggle": false,
      "condition": "",
      "mame_label": "P1 Button 3",
      "mame_type": "62",
      "mame_tag": ":P1",
      "cfg_tag": ":P1"
    },
    {
      "input": "BUTTON1",
      "input_id": "P1_BUTTON1",
      "label": "phaser",
      "function": "phaser",
      "control_type": "only_buttons",
      "joystick_way": "",
      "port_block": "starcrus",
      "tag": "P1",
      "mask": "0x40",
      "mask_int": 64,
      "defvalue": "0x40",
      "defvalue_int": 64,
      "default_raw": "IP_ACTIVE_LOW",
      "ipt": "IPT_BUTTON1",
      "keycode": "",
      "keycode_dec": "",
      "keycode_inc": "",
      "comment": "phaser",
      "player": 1,
      "min": null,
      "max": null,
      "sensitivity": null,
      "keydelta": null,
      "centerdelta": null,
      "full_turn_count": null,
      "impulse": null,
      "reverse": false,
      "invert": false,
      "reset": false,
      "toggle": false,
      "condition": "",
      "mame_label": "P1 Button 1",
      "mame_type": "60",
      "mame_tag": ":P1",
      "cfg_tag": ":P1"
    },
    {
      "input": "JOYSTICK_LEFT",
      "input_id": "P2_JOYSTICK_LEFT",
      "label": "ccw",
      "function": "ccw",
      "control_type": "joy2wayhorizontal",
      "joystick_way": "2way",
      "port_block": "starcrus",
      "tag": "P2",
      "mask": "0x1",
      "mask_int": 1,
      "defvalue": "0x1",
      "defvalue_int": 1,
      "default_raw": "IP_ACTIVE_LOW",
      "ipt": "IPT_JOYSTICK_LEFT",
      "keycode": "",
      "keycode_dec": "",
      "keycode_inc": "",
      "comment": "ccw",
      "player": 2,
      "min": null,
      "max": null,
      "sensitivity": null,
      "keydelta": null,
      "centerdelta": null,
      "full_turn_count": null,
      "impulse": null,
      "reverse": false,
      "invert": false,
      "reset": false,
      "toggle": false,
      "condition": "",
      "mame_label": "P2 Left",
      "mame_type": "49",
      "mame_tag": ":P2",
      "cfg_tag": ":P2"
    },
    {
      "input": "BUTTON2",
      "input_id": "P2_BUTTON2",
      "label": "engine",
      "function": "engine",
      "control_type": "only_buttons",
      "joystick_way": "",
      "port_block": "starcrus",
      "tag": "P2",
      "mask": "0x2",
      "mask_int": 2,
      "defvalue": "0x2",
      "defvalue_int": 2,
      "default_raw": "IP_ACTIVE_LOW",
      "ipt": "IPT_BUTTON2",
      "keycode": "",
      "keycode_dec": "",
      "keycode_inc": "",
      "comment": "engine",
      "player": 2,
      "min": null,
      "max": null,
      "sensitivity": null,
      "keydelta": null,
      "centerdelta": null,
      "full_turn_count": null,
      "impulse": null,
      "reverse": false,
      "invert": false,
      "reset": false,
      "toggle": false,
      "condition": "",
      "mame_label": "P2 Button 2",
      "mame_type": "61",
      "mame_tag": ":P2",
      "cfg_tag": ":P2"
    },
    {
      "input": "JOYSTICK_RIGHT",
      "input_id": "P2_JOYSTICK_RIGHT",
      "label": "cw",
      "function": "cw",
      "control_type": "joy2wayhorizontal",
      "joystick_way": "2way",
      "port_block": "starcrus",
      "tag": "P2",
      "mask": "0x4",
      "mask_int": 4,
      "defvalue": "0x4",
      "defvalue_int": 4,
      "default_raw": "IP_ACTIVE_LOW",
      "ipt": "IPT_JOYSTICK_RIGHT",
      "keycode": "",
      "keycode_dec": "",
      "keycode_inc": "",
      "comment": "cw",
      "player": 2,
      "min": null,
      "max": null,
      "sensitivity": null,
      "keydelta": null,
      "centerdelta": null,
      "full_turn_count": null,
      "impulse": null,
      "reverse": false,
      "invert": false,
      "reset": false,
      "toggle": false,
      "condition": "",
      "mame_label": "P2 Right",
      "mame_type": "50",
      "mame_tag": ":P2",
      "cfg_tag": ":P2"
    },
    {
      "input": "BUTTON3",
      "input_id": "P2_BUTTON3",
      "label": "torpedo",
      "function": "torpedo",
      "control_type": "only_buttons",
      "joystick_way": "",
      "port_block": "starcrus",
      "tag": "P2",
      "mask": "0x10",
      "mask_int": 16,
      "defvalue": "0x10",
      "defvalue_int": 16,
      "default_raw": "IP_ACTIVE_LOW",
      "ipt": "IPT_BUTTON3",
      "keycode": "",
      "keycode_dec": "",
      "keycode_inc": "",
      "comment": "torpedo",
      "player": 2,
      "min": null,
      "max": null,
      "sensitivity": null,
      "keydelta": null,
      "centerdelta": null,
      "full_turn_count": null,
      "impulse": null,
      "reverse": false,
      "invert": false,
      "reset": false,
      "toggle": false,
      "condition": "",
      "mame_label": "P2 Button 3",
      "mame_type": "62",
      "mame_tag": ":P2",
      "cfg_tag": ":P2"
    },
    {
      "input": "BUTTON1",
      "input_id": "P2_BUTTON1",
      "label": "phaser",
      "function": "phaser",
      "control_type": "only_buttons",
      "joystick_way": "",
      "port_block": "starcrus",
      "tag": "P2",
      "mask": "0x40",
      "mask_int": 64,
      "defvalue": "0x40",
      "defvalue_int": 64,
      "default_raw": "IP_ACTIVE_LOW",
      "ipt": "IPT_BUTTON1",
      "keycode": "",
      "keycode_dec": "",
      "keycode_inc": "",
      "comment": "phaser",
      "player": 2,
      "min": null,
      "max": null,
      "sensitivity": null,
      "keydelta": null,
      "centerdelta": null,
      "full_turn_count": null,
      "impulse": null,
      "reverse": false,
      "invert": false,
      "reset": false,
      "toggle": false,
      "condition": "",
      "mame_label": "P2 Button 1",
      "mame_type": "60",
      "mame_tag": ":P2",
      "cfg_tag": ":P2"
    }
  ],
  "outputs": [
    {
      "name": "led2",
      "label": "Led2",
      "function": "led2",
      "physical_type": "led",
      "value_type": "boolean",
      "families": [
        "led"
      ],
      "group": "",
      "usage": "",
      "player": null,
      "index": 2,
      "panel_index": 2,
      "color": "",
      "side": ""
    }
  ],
  "mappings": []
}
